Workbook

Sheet Catalogos
A1: Nombre | B1: Cantidad | C1: ProrRateo en meses | D1: Costo unitario | E1: Costo mensual | H1: Nombre | I1: Cantidad
A2: Botas de seguridad | B2: 1 | C2: 12 | D2: 2500 | E2: =D2/C2 -> 208.33333 | H2: Transporte | I2: 800
A3: Casco | B3: 1 | C3: 6 | D3: 500 | E3: =D3/C3 -> 83.333333 | H3: Alimentación | I3: 1000
A4: Guantes | B4: 2 | C4: 4 | D4: 650 | E4: =D4/C4 -> 162.5 | H4: Telefono | I4: 250
A5: Camisas | B5: 3 | C5: 4 | D5: 450 | E5: =D5/C5 -> 112.5 | H5: Combustible | I5: 0
A6: Gafas | B6: 2 | C6: 4 | D6: 900 | E6: =D6/C6 -> 225 | H6: Depresiasión | I6: 0
A7: Cuchillas | B7: 1 | C7: 3 | D7: 200 | E7: =D7/C7 -> 66.666667 | H7: Ninguno | I7: 0
A8: Cinturon | B8: 1 | C8: 8 | D8: 750 | E8: =D8/C8 -> 93.75
A9: Chalecos de alta visibilidad | B9: 1 | C9: 4 | D9: 250 | E9: =D9/C9 -> 62.5
A10: Arneses de seguridad | B10: 1 | C10: 6 | D10: 600 | E10: =D10/C10 -> 100
A11: Protectores faciales | B11: 1 | C11: 6 | D11: 800 | E11: =D11/C11 -> 133.33333
A12: Protección respiratoria | B12: 1 | C12: 6 | D12: 1500 | E12: =D12/C12 -> 250
A13: Protectores térmicos | B13: 1 | C13: 12 | D13: 6000 | E13: =D13/C13 -> 500

Sheet Tarifario
A2: Tarifario de costos de facturación por horas laboradas
A3: COSTOS UNITARIOS | H3: Viaticos | L3: EPP
H4: Previsto | L4: Previsto
A5: Salario base | B5: 9000 | E5: Utilidad | F5: 20 | H5: Totales | J5: =SUM(J6:J12) -> 1800 | L5: Totales | N5: Precio | O5: Factor rep | P5: =SUM(P6:P12) -> 1472.1875
A6: Gastos Oerativos | H6: Transporte | J6: =VLOOKUP(H6,Catalogos!$H$2:$I$13,2,FALSE) -> 800 | L6: Guantes | N6: =VLOOKUP(L6,Catalogos!$A$2:$E$13,5,FALSE) -> 162.5 | O6: 0.05 | P6: =(N6*O6)+N6 -> 170.625
A7: Prestaciones | B7: Viáticos | C7: Epp | D7: Supervicion | E7: Cargos | F7: Seguros | H7: Alimentación | J7: =VLOOKUP(H7,Catalogos!$H$2:$I$13,2,FALSE) -> 1000 | L7: Camisas | N7: =VLOOKUP(L7,Catalogos!$A$2:$E$13,5,FALSE) -> 112.5 | O7: 0.05 | P7: =(N7*O7)+N7 -> 118.125
A8: =(B5*0.743) -> 6687 | B8: =J5 -> 1800 | C8: =P5 -> 1472.1875 | D8: 1000 | E8: 500 | F8: 300 | H8: Ninguno | J8: =VLOOKUP(H8,Catalogos!$H$2:$I$13,2,FALSE) -> 0 | L8: Botas de seguridad | N8: =VLOOKUP(L8,Catalogos!$A$2:$E$13,5,FALSE) -> 208.33333 | O8: 0.05 | P8: =(N8*O8)+N8 -> 218.75
A9: Costo mensual | B9: Utilidad | C9: Costos Totales | D9: Costo diario | E9: Costo hora | F9: Costo extra | H9: Ninguno | J9: =VLOOKUP(H9,Catalogos!$H$2:$I$13,2,FALSE) -> 0 | L9: Gafas | N9: =VLOOKUP(L9,Catalogos!$A$2:$E$13,5,FALSE) -> 225 | O9: 0.05 | P9: =(N9*O9)+N9 -> 236.25
A10: =A8+B8+C8+D8+E8+F8+B5 -> 20759.188 | B10: =(B5/(1-(F5/100)))-B5 -> 2250 | C10: =A10+B10 -> 23009.188 | D10: =C10/30 -> 766.97292 | E10: =D10/8 -> 95.871615 | F10: =((B5/30)/8)+E10 -> 133.37161 | H10: Ninguno | J10: =VLOOKUP(H10,Catalogos!$H$2:$I$13,2,FALSE) -> 0 | L10: Cinturon | N10: =VLOOKUP(L10,Catalogos!$A$2:$E$13,5,FALSE) -> 93.75 | O10: 0.05 | P10: =(N10*O10)+N10 -> 98.4375
H11: Ninguno | J11: =VLOOKUP(H11,Catalogos!$H$2:$I$13,2,FALSE) -> 0 | L11: Protectores térmicos | N11: =VLOOKUP(L11,Catalogos!$A$2:$E$13,5,FALSE) -> 500 | O11: 0.05 | P11: =(N11*O11)+N11 -> 525
H12: Ninguno | J12: =VLOOKUP(H12,Catalogos!$H$2:$I$13,2,FALSE) -> 0 | L12: Arneses de seguridad | N12: =VLOOKUP(L12,Catalogos!$A$2:$E$13,5,FALSE) -> 100 | O12: 0.05 | P12: =(N12*O12)+N12 -> 105
F16: =IF(ISBLANK($M6), "", SUMIF(Transacciones!$E:$E,$M6,Transacciones!$C:$C))
F17: =IF(ISBLANK($M7), "", SUMIF(Transacciones!$E:$E,$M7,Transacciones!$C:$C))
F18: =IF(ISBLANK($M8), "", SUMIF(Transacciones!$E:$E,$M8,Transacciones!$C:$C))
F19: =IF(ISBLANK($M9), "", SUMIF(Transacciones!$E:$E,$M9,Transacciones!$C:$C))
F20: =IF(ISBLANK($M10), "", SUMIF(Transacciones!$E:$E,$M10,Transacciones!$C:$C))
F21: =IF(ISBLANK($M11), "", SUMIF(Transacciones!$E:$E,$M11,Transacciones!$C:$C))
F22: =IF(ISBLANK($M12), "", SUMIF(Transacciones!$E:$E,$M12,Transacciones!$C:$C))
