Workbook

Sheet Catalogos
A1: Nombre | B1: Cantidad | C1: ProrRateo en meses | D1: Costo unitario | E1: Costo mensual | H1: Nombre | I1: Cantidad
A2: Botas de seguridad | B2: 1 | C2: 12 | D2: 2500 | E2: =D2/C2 -> C$208.33 | H2: Transporte | I2: 800
A3: Casco | B3: 1 | C3: 6 | D3: 500 | E3: =D3/C3 -> C$83.33 | H3: Alimentación | I3: 1000
A4: Guantes | B4: 2 | C4: 4 | D4: 650 | E4: =D4/C4 -> C$162.50 | H4: Telefono | I4: 250
A5: Camisas | B5: 3 | C5: 4 | D5: 450 | E5: =D5/C5 -> C$112.50 | H5: Combustible | I5: 0
A6: Gafas | B6: 2 | C6: 4 | D6: 900 | E6: =D6/C6 -> C$225.00 | H6: Depresiasión | I6: 0
A7: Cuchillas | B7: 1 | C7: 3 | D7: 200 | E7: =D7/C7 -> C$66.67 | H7: Ninguno | I7: 0
A8: Cinturon | B8: 1 | C8: 8 | D8: 750 | E8: =D8/C8 -> C$93.75
A9: Chalecos de alta visibilidad | B9: 1 | C9: 4 | D9: 250 | E9: =D9/C9 -> C$62.50
A10: Arneses de seguridad | B10: 1 | C10: 6 | D10: 600 | E10: =D10/C10 -> C$100.00
A11: Protectores faciales | B11: 1 | C11: 6 | D11: 800 | E11: =D11/C11 -> C$133.33
A12: Protección respiratoria | B12: 1 | C12: 6 | D12: 1500 | E12: =D12/C12 -> C$250.00
A13: Protectores térmicos | B13: 1 | C13: 12 | D13: 6000 | E13: =D13/C13 -> C$500.00

Sheet Tarifario
A2: Tarifario de costos de facturación por horas laboradas
H4: COSTOS UNITARIOS
A6: Cantidad | C6: OTRA INFORMACIÓN | H6: Salario base | I6: 8341 | L6: Utilidad | M6: 20
H7: Gastos Oerativos
H8: Prestaciones | I8: Viáticos | J8: Epp | K8: Supervicion | L8: Cargos | M8: Seguros
H9: =(I6*0.72) -> 6005.52 | I9: =G16 -> 1800.00 | J9: =C16 -> 1402.08 | K9: 1000 | L9: 500 | M9: 300
H10: Costo mensual | I10: Utilidad | J10: Costos Totales | K10: Costo diario | L10: Costo hora | M10: Costo extra
H11: =H9+I9+J9+K9+L9+M9+I6 -> 19348.60 | I11: =(I6/(1-(M6/100)))-I6 -> 2085.25 | J11: =H11+I11 -> 21433.85 | K11: =J11/30 -> 714.46 | L11: =K11/8 -> 89.31 | M11: =((I6/30)/8)+L11 -> 124.06
A14: EPP | E14: Viaticos
A15: Previsto | E15: Previsto
A16: Totales | C16: =SUM(C17:C989) -> 1,402.08 | E16: Totales | G16: =SUM(G17:G989) -> 1,800.00
A17: Guantes | C17: =VLOOKUP(A17,Catalogos!$A$2:$E$13,5,FALSE) -> 162.50 | D17: =IF(ISBLANK($B17), "", SUMIF(Transacciones!$E:$E,$B17,Transacciones!$C:$C)) | E17: Transporte | G17: =VLOOKUP(E17,Catalogos!$H$2:$I$13,2,FALSE) -> 800.00
A18: Camisas | C18: =VLOOKUP(A18,Catalogos!$A$2:$E$13,5,FALSE) -> 112.50 | D18: =IF(ISBLANK($B18), "", SUMIF(Transacciones!$E:$E,$B18,Transacciones!$C:$C)) | E18: Alimentación | G18: =VLOOKUP(E18,Catalogos!$H$2:$I$13,2,FALSE) -> 1,000.00
A19: Botas de seguridad | C19: =VLOOKUP(A19,Catalogos!$A$2:$E$13,5,FALSE) -> 208.33 | D19: =IF(ISBLANK($B19), "", SUMIF(Transacciones!$E:$E,$B19,Transacciones!$C:$C)) | E19: Ninguno | G19: =VLOOKUP(E19,Catalogos!$H$2:$I$13,2,FALSE) -> 0.00
A20: Gafas | C20: =VLOOKUP(A20,Catalogos!$A$2:$E$13,5,FALSE) -> 225.00 | D20: =IF(ISBLANK($B20), "", SUMIF(Transacciones!$E:$E,$B20,Transacciones!$C:$C)) | E20: Ninguno | G20: =VLOOKUP(E20,Catalogos!$H$2:$I$13,2,FALSE) -> 0.00
A21: Cinturon | C21: =VLOOKUP(A21,Catalogos!$A$2:$E$13,5,FALSE) -> 93.75 | D21: =IF(ISBLANK($B21), "", SUMIF(Transacciones!$E:$E,$B21,Transacciones!$C:$C)) | E21: Ninguno | G21: =VLOOKUP(E21,Catalogos!$H$2:$I$13,2,FALSE) -> 0.00
A22: Protectores térmicos | C22: =VLOOKUP(A22,Catalogos!$A$2:$E$13,5,FALSE) -> 500.00 | D22: =IF(ISBLANK($B22), "", SUMIF(Transacciones!$E:$E,$B22,Transacciones!$C:$C)) | E22: Ninguno | G22: =VLOOKUP(E22,Catalogos!$H$2:$I$13,2,FALSE) -> 0.00
A23: Arneses de seguridad | C23: =VLOOKUP(A23,Catalogos!$A$2:$E$13,5,FALSE) -> 100.00 | D23: =IF(ISBLANK($B23), "", SUMIF(Transacciones!$E:$E,$B23,Transacciones!$C:$C)) | E23: Ninguno | G23: =VLOOKUP(E23,Catalogos!$H$2:$I$13,2,FALSE) -> 0.00

Sheet Hoja 5
A4: Guantes | C4: =VLOOKUP(A4,Catalogos!$A$2:$E$13,5,FALSE) -> 162.50
A5: Camisas | C5: =VLOOKUP(A5,Catalogos!$A$2:$E$13,5,FALSE) -> 112.50
A6: Botas de seguridad | C6: =VLOOKUP(A6,Catalogos!$A$2:$E$13,5,FALSE) -> 208.33
A7: Gafas | C7: =VLOOKUP(A7,Catalogos!$A$2:$E$13,5,FALSE) -> 225.00
A8: Cinturon | C8: =VLOOKUP(A8,Catalogos!$A$2:$E$13,5,FALSE) -> 93.75
A9: Protectores térmicos | C9: =VLOOKUP(A9,Catalogos!$A$2:$E$13,5,FALSE) -> 500.00
A10: Arneses de seguridad | C10: =VLOOKUP(A10,Catalogos!$A$2:$E$13,5,FALSE) -> 100.00
